twilio_helper/__init__.py
twilio_helper/main.py
twilio_helper-0.1.0.dist-info/LICENSE
twilio_helper-0.1.0.dist-info/METADATA
twilio_helper-0.1.0.dist-info/WHEEL
twilio_helper-0.1.0.dist-info/RECORD
