Metadata-Version: 2.3
Name: twilio-helper
Version: 0.1.0
Summary: A lightweight Python utility that simplifies sending WhatsApp messages using the Twilio API. It provides built-in credential validation and a clean interface for sending messages, making it easy to integrate into alerting systems, bots, and automation scripts.
License: MIT
Keywords: twilio,whatsapp,messaging,automation,alert,notification
Author: Lav Sharma
Author-email: lavsharma2016@gmail.com
Requires-Python: >=3.12
Classifier: Programming Language :: Python :: 3
Classifier: Programming Language :: Python :: 3.12
Classifier: License :: OSI Approved :: MIT License
Classifier: Operating System :: OS Independent
Classifier: Topic :: Communications :: Chat
Classifier: Intended Audience :: Developers
Requires-Dist: twilio (>=9.5.2,<10.0.0)
Project-URL: Homepage, https://github.com/lavsharma/twilio-helper
Project-URL: Issues, https://github.com/lavsharma/twilio-helper/issues
Project-URL: Repository, https://github.com/lavsharma/twilio-helper
